elasticsearch_tool/__init__.py
elasticsearch_tool/config.py
elasticsearch_tool/base_element/__init__.py
elasticsearch_tool/base_element/elements.py
elasticsearch_tool/base_element/exceptions.py
elasticsearch_tool/base_element/operate.py
elasticsearch_tool/base_element/sql_tools.py
elasticsearch_tool/elements/__init__.py
elasticsearch_tool/elements/document.py
elasticsearch_tool-0.9.9.dist-info/LICENSE
elasticsearch_tool-0.9.9.dist-info/METADATA
elasticsearch_tool-0.9.9.dist-info/WHEEL
elasticsearch_tool-0.9.9.dist-info/top_level.txt
elasticsearch_tool-0.9.9.dist-info/RECORD
