Metadata-Version: 2.1
Name: elasticsearch-tool
Version: 0.9.9
Summary: some like orm for elasticsearch, elasticsearch的辅助工具, 提供类似ORM的操作方式, 此版本提高了稳定性,解决了出现的bug
Home-page: https://github.com/pypa/sampleproject
Author: haiton
Author-email: 642641850@qq.com
License: UNKNOWN
Platform: UNKNOWN
Classifier: Programming Language :: Python :: 3
Classifier: License :: OSI Approved :: GNU General Public License v3 (GPLv3)
Classifier: Operating System :: OS Independent
Requires-Python: >=3.6
Requires-Dist: elasticsearch (==5.0.0)
